STARS2025/lab09/source/fa.sv
`default_nettype none
module fa (
  input logic A, B, Cin,
  output logic S, Cout
);
  assign S = A ^ B ^ Cin;
  assign Cout = (A & B) | (Cin & (A ^ B));
endmodule

STARS2025/lab08/source/fa4.sv
`default_nettype none
module fa4 (
  input logic [3:0] A, B,
  input logic Cin,
  output logic [3:0] S,
  output logic Cout
);
  logic [2:0] C;
  fa adder1 (
    .A(A[0]), .B(B[0]), .Cin(Cin),
    .S(S[0]), .Cout(C[0])
  );
  fa adder2 (
    .A(A[1]), .B(B[1]), .Cin(C[0]),
    .S(S[1]), .Cout(C[1])
  );
  fa adder3 (
    .A(A[2]), .B(B[2]), .Cin(C[1]),   
    .S(S[2]), .Cout(C[2])
  );
  fa adder4 (
    .A(A[3]), .B(B[3]), .Cin(C[2]),
    .S(S[3]), .Cout(Cout)
  );
endmodule

STARS2025/lab08/testbench/fa4_tb.sv
`timescale 1ms/10ps
module fa4_tb;
  logic [3:0] A, B, S;
  logic Cin, Cout;
  fa4 fulladder (.A(A), .B(B), .Cin(Cin), .S(S), .Cout(Cout));
  initial begin
    // make sure to dump the signals so we can see them in the waveform
    $dumpfile("waves/fa4.vcd"); // change the vcd file name to your source file name
    $dumpvars(0, fa4_tb);
    // for loop to test all possible inputs
    for (integer i = 0; i < 16; i++) begin
      for (integer j = 0; j < 16; j++) begin
        for (integer k = 0; k <= 1; k++) begin
          // set our input signals
          A = i; B = j; Cin = k;
          #1;
          // display inputs and outputs
          $display("A=\%b, B=\%b, Cin=\%b, Cout=\%b, S=\%b", A, B, Cin, Cout, S);
        end
      end
    end
    // finish the simulation
    #1 $finish;
  end
endmodule

STARS2025/lab08/waves/fa4.vcd
$date
	Wed Jun 18 15:10:58 2025
$end
$version
	Icarus Verilog
$end
$timescale
	10ps
$end
$scope module fa4_tb $end
$var wire 4 ! S [3:0] $end
$var wire 1 " Cout $end
$var reg 4 # A [3:0] $end
$var reg 4 $ B [3:0] $end
$var reg 1 % Cin $end
$scope module fulladder $end
$var wire 4 & A [3:0] $end
$var wire 4 ' B [3:0] $end
$var wire 1 % Cin $end
$var wire 4 ( S [3:0] $end
$var wire 1 " Cout $end
$var wire 3 ) C [2:0] $end
$scope module adder1 $end
$var wire 1 * A $end
$var wire 1 + B $end
$var wire 1 % Cin $end
$var wire 1 , Cout $end
$var wire 1 - S $end
$upscope $end
$scope module adder2 $end
$var wire 1 . A $end
$var wire 1 / B $end
$var wire 1 0 Cin $end
$var wire 1 1 Cout $end
$var wire 1 2 S $end
$upscope $end
$scope module adder3 $end
$var wire 1 3 A $end
$var wire 1 4 B $end
$var wire 1 5 Cin $end
$var wire 1 6 Cout $end
$var wire 1 7 S $end
$upscope $end
$scope module adder4 $end
$var wire 1 8 A $end
$var wire 1 9 B $end
$var wire 1 : Cin $end
$var wire 1 " Cout $end
$var wire 1 ; S $end
$upscope $end
$upscope $end
$scope begin $ivl_for_loop0 $end
$var integer 32 < i [31:0] $end
$scope begin $ivl_for_loop1 $end
$var integer 32 = j [31:0] $end
$scope begin $ivl_for_loop2 $end
$var integer 32 > k [31:0] $end
$upscope $end
$upscope $end
$upscope $end
$upscope $end
$enddefinitions $end
$comment Show the parameter values. $end
$dumpall
$end
#0
$dumpvars
b0 >
b0 =
b0 <
0;
0:
09
08
07
06
05
04
03
02
01
00
0/
0.
0-
0,
0+
0*
b0 )
b0 (
b0 '
b0 &
0%
b0 $
b0 #
0"
b0 !
$end
#100000000
b1 !
b1 (
1-
1%
b1 >
#200000000
b1 !
b1 (
1-
1+
0%
b1 $
b1 '
b1 =
b0 >
#300000000
12
10
b1 )
1,
b10 !
b10 (
0-
1%
b1 >
#400000000
07
05
01
00
12
b0 )
0,
b10 !
b10 (
0-
0+
1/
0%
b10 $
b10 '
b10 =
b0 >
#500000000
b11 !
b11 (
1-
1%
b1 >
#600000000
b11 !
b11 (
1-
1+
0%
b11 $
b11 '
b11 =
b0 >
#700000000
17
15
11
02
10
b11 )
1,
b100 !
b100 (
0-
1%
b1 >
#800000000
0;
05
0:
01
06
00
02
17
b0 )
0,
b100 !
b100 (
0-
0+
0/
14
0%
b100 $
b100 '
b100 =
b0 >
#900000000
b101 !
b101 (
1-
1%
b1 >
#1000000000
b101 !
b101 (
1-
1+
0%
b101 $
b101 '
b101 =
b0 >
#1100000000
12
10
b1 )
1,
b110 !
b110 (
0-
1%
b1 >
#1200000000
0;
0:
06
17
05
01
00
12
b0 )
0,
b110 !
b110 (
0-
0+
1/
0%
b110 $
b110 '
b110 =
b0 >
#1300000000
b111 !
b111 (
1-
1%
b1 >
#1400000000
b111 !
b111 (
1-
1+
0%
b111 $
b111 '
b111 =
b0 >
#1500000000
1;
1:
16
07
15
11
02
10
b111 )
1,
b1000 !
b1000 (
0-
1%
b1 >
#1600000000
05
0:
01
06
0"
00
02
07
1;
b0 )
0,
b1000 !
b1000 (
0-
0+
0/
04
19
0%
b1000 $
b1000 '
b1000 =
b0 >
#1700000000
b1001 !
b1001 (
1-
1%
b1 >
#1800000000
b1001 !
b1001 (
1-
1+
0%
b1001 $
b1001 '
b1001 =
b0 >
#1900000000
12
10
b1 )
1,
b1010 !
b1010 (
0-
1%
b1 >
#2000000000
07
05
01
00
12
b0 )
0,
b1010 !
b1010 (
0-
0+
1/
0%
b1010 $
b1010 '
b1010 =
b0 >
#2100000000
b1011 !
b1011 (
1-
1%
b1 >
#2200000000
b1011 !
b1011 (
1-
1+
0%
b1011 $
b1011 '
b1011 =
b0 >
#2300000000
17
15
11
02
10
b11 )
1,
b1100 !
b1100 (
0-
1%
b1 >
#2400000000
0"
1;
05
0:
01
06
00
02
17
b0 )
0,
b1100 !
b1100 (
0-
0+
0/
14
0%
b1100 $
b1100 '
b1100 =
b0 >
#2500000000
b1101 !
b1101 (
1-
1%
b1 >
#2600000000
b1101 !
b1101 (
1-
1+
0%
b1101 $
b1101 '
b1101 =
b0 >
#2700000000
12
10
b1 )
1,
b1110 !
b1110 (
0-
1%
b1 >
#2800000000
0"
1;
0:
06
17
05
01
00
12
b0 )
0,
b1110 !
b1110 (
0-
0+
1/
0%
b1110 $
b1110 '
b1110 =
b0 >
#2900000000
b1111 !
b1111 (
1-
1%
b1 >
#3000000000
b1111 !
b1111 (
1-
1+
0%
b1111 $
b1111 '
b1111 =
b0 >
#3100000000
1"
0;
1:
16
07
15
11
02
10
b111 )
1,
b0 !
b0 (
0-
1%
b1 >
#3200000000
05
0:
01
06
0"
00
02
07
0;
b0 )
0,
b1 !
b1 (
1-
0+
0/
04
09
1*
0%
b0 $
b0 '
b1 #
b1 &
b1 <
b0 =
b0 >
#3300000000
12
10
b1 )
1,
b10 !
b10 (
0-
1%
b1 >
#3400000000
b10 !
b10 (
0-
1+
0%
b1 $
b1 '
b1 =
b0 >
#3500000000
b11 !
b11 (
1-
1%
b1 >
#3600000000
07
05
00
01
b0 )
0,
12
b11 !
b11 (
1-
0+
1/
0%
b10 $
b10 '
b10 =
b0 >
#3700000000
17
15
11
02
10
b11 )
1,
b100 !
b100 (
0-
1%
b1 >
#3800000000
b100 !
b100 (
0-
1+
0%
b11 $
b11 '
b11 =
b0 >
#3900000000
b101 !
b101 (
1-
1%
b1 >
#4000000000
0;
05
0:
00
01
06
b0 )
0,
02
17
b101 !
b101 (
1-
0+
0/
14
0%
b100 $
b100 '
b100 =
b0 >
#4100000000
12
10
b1 )
1,
b110 !
b110 (
0-
1%
b1 >
#4200000000
b110 !
b110 (
0-
1+
0%
b101 $
b101 '
b101 =
b0 >
#4300000000
b111 !
b111 (
1-
1%
b1 >
#4400000000
0;
0:
06
17
05
00
01
b0 )
0,
12
b111 !
b111 (
1-
0+
1/
0%
b110 $
b110 '
b110 =
b0 >
#4500000000
1;
1:
16
07
15
11
02
10
b111 )
1,
b1000 !
b1000 (
0-
1%
b1 >
#4600000000
b1000 !
b1000 (
0-
1+
0%
b111 $
b111 '
b111 =
b0 >
#4700000000
b1001 !
b1001 (
1-
1%
b1 >
#4800000000
05
0:
00
01
06
0"
b0 )
0,
02
07
1;
b1001 !
b1001 (
1-
0+
0/
04
19
0%
b1000 $
b1000 '
b1000 =
b0 >
#4900000000
12
10
b1 )
1,
b1010 !
b1010 (
0-
1%
b1 >
#5000000000
b1010 !
b1010 (
0-
1+
0%
b1001 $
b1001 '
b1001 =
b0 >
#5100000000
b1011 !
b1011 (
1-
1%
b1 >
#5200000000
07
05
00
01
b0 )
0,
12
b1011 !
b1011 (
1-
0+
1/
0%
b1010 $
b1010 '
b1010 =
b0 >
#5300000000
17
15
11
02
10
b11 )
1,
b1100 !
b1100 (
0-
1%
b1 >
#5400000000
b1100 !
b1100 (
0-
1+
0%
b1011 $
b1011 '
b1011 =
b0 >
#5500000000
b1101 !
b1101 (
1-
1%
b1 >
#5600000000
0"
1;
05
0:
00
01
06
b0 )
0,
02
17
b1101 !
b1101 (
1-
0+
0/
14
0%
b1100 $
b1100 '
b1100 =
b0 >
#5700000000
12
10
b1 )
1,
b1110 !
b1110 (
0-
1%
b1 >
#5800000000
b1110 !
b1110 (
0-
1+
0%
b1101 $
b1101 '
b1101 =
b0 >
#5900000000
b1111 !
b1111 (
1-
1%
b1 >
#6000000000
0"
1;
0:
06
17
05
00
01
b0 )
0,
12
b1111 !
b1111 (
1-
0+
1/
0%
b1110 $
b1110 '
b1110 =
b0 >
#6100000000
1"
0;
1:
16
07
15
11
02
10
b111 )
1,
b0 !
b0 (
0-
1%
b1 >
#6200000000
b0 !
b0 (
0-
1+
0%
b1111 $
b1111 '
b1111 =
b0 >
#6300000000
b1 !
b1 (
1-
1%
b1 >
#6400000000
05
01
0:
12
06
0"
00
07
0;
b0 )
0,
b10 !
b10 (
0-
0+
0/
04
09
0*
1.
0%
b0 $
b0 '
b10 #
b10 &
b10 <
b0 =
b0 >
#6500000000
b11 !
b11 (
1-
1%
b1 >
#6600000000
b11 !
b11 (
1-
1+
0%
b1 $
b1 '
b1 =
b0 >
#6700000000
17
15
11
02
10
b11 )
1,
b100 !
b100 (
0-
1%
b1 >
#6800000000
00
02
b10 )
0,
b100 !
b100 (
0-
0+
1/
0%
b10 $
b10 '
b10 =
b0 >
#6900000000
b101 !
b101 (
1-
1%
b1 >
#7000000000
b101 !
b101 (
1-
1+
0%
b11 $
b11 '
b11 =
b0 >
#7100000000
12
10
b11 )
1,
b110 !
b110 (
0-
1%
b1 >
#7200000000
05
0;
01
0:
06
00
12
17
b0 )
0,
b110 !
b110 (
0-
0+
0/
14
0%
b100 $
b100 '
b100 =
b0 >
#7300000000
b111 !
b111 (
1-
1%
b1 >
#7400000000
b111 !
b111 (
1-
1+
0%
b101 $
b101 '
b101 =
b0 >
#7500000000
1;
1:
16
07
15
11
02
10
b111 )
1,
b1000 !
b1000 (
0-
1%
b1 >
#7600000000
00
02
b110 )
0,
b1000 !
b1000 (
0-
0+
1/
0%
b110 $
b110 '
b110 =
b0 >
#7700000000
b1001 !
b1001 (
1-
1%
b1 >
#7800000000
b1001 !
b1001 (
1-
1+
0%
b111 $
b111 '
b111 =
b0 >
#7900000000
12
10
b111 )
1,
b1010 !
b1010 (
0-
1%
b1 >
#8000000000
05
01
0:
06
0"
00
12
07
1;
b0 )
0,
b1010 !
b1010 (
0-
0+
0/
04
19
0%
b1000 $
b1000 '
b1000 =
b0 >
#8100000000
b1011 !
b1011 (
1-
1%
b1 >
#8200000000
b1011 !
b1011 (
1-
1+
0%
b1001 $
b1001 '
b1001 =
b0 >
#8300000000
17
15
11
02
10
b11 )
1,
b1100 !
b1100 (
0-
1%
b1 >
#8400000000
00
02
b10 )
0,
b1100 !
b1100 (
0-
0+
1/
0%
b1010 $
b1010 '
b1010 =
b0 >
#8500000000
b1101 !
b1101 (
1-
1%
b1 >
#8600000000
b1101 !
b1101 (
1-
1+
0%
b1011 $
b1011 '
b1011 =
b0 >
#8700000000
12
10
b11 )
1,
b1110 !
b1110 (
0-
1%
b1 >
#8800000000
0"
05
1;
01
0:
06
00
12
17
b0 )
0,
b1110 !
b1110 (
0-
0+
0/
14
0%
b1100 $
b1100 '
b1100 =
b0 >
#8900000000
b1111 !
b1111 (
1-
1%
b1 >
#9000000000
b1111 !
b1111 (
1-
1+
0%
b1101 $
b1101 '
b1101 =
b0 >
#9100000000
1"
0;
1:
16
07
15
11
02
10
b111 )
1,
b0 !
b0 (
0-
1%
b1 >
#9200000000
00
02
b110 )
0,
b0 !
b0 (
0-
0+
1/
0%
b1110 $
b1110 '
b1110 =
b0 >
#9300000000
b1 !
b1 (
1-
1%
b1 >
#9400000000
b1 !
b1 (
1-
1+
0%
b1111 $
b1111 '
b1111 =
b0 >
#9500000000
12
10
b111 )
1,
b10 !
b10 (
0-
1%
b1 >
#9600000000
05
01
0:
06
0"
00
12
07
0;
b0 )
0,
b11 !
b11 (
1-
0+
0/
04
09
1*
0%
b0 $
b0 '
b11 #
b11 &
b11 <
b0 =
b0 >
#9700000000
17
15
11
02
10
b11 )
1,
b100 !
b100 (
0-
1%
b1 >
#9800000000
b100 !
b100 (
0-
1+
0%
b1 $
b1 '
b1 =
b0 >
#9900000000
b101 !
b101 (
1-
1%
b1 >
#10000000000
00
b10 )
0,
02
b101 !
b101 (
1-
0+
1/
0%
b10 $
b10 '
b10 =
b0 >
#10100000000
12
10
b11 )
1,
b110 !
b110 (
0-
1%
b1 >
#10200000000
b110 !
b110 (
0-
1+
0%
b11 $
b11 '
b11 =
b0 >
#10300000000
b111 !
b111 (
1-
1%
b1 >
#10400000000
05
01
0;
0:
00
06
b0 )
0,
12
17
b111 !
b111 (
1-
0+
0/
14
0%
b100 $
b100 '
b100 =
b0 >
#10500000000
1;
1:
16
07
15
11
02
10
b111 )
1,
b1000 !
b1000 (
0-
1%
b1 >
#10600000000
b1000 !
b1000 (
0-
1+
0%
b101 $
b101 '
b101 =
b0 >
#10700000000
b1001 !
b1001 (
1-
1%
b1 >
#10800000000
00
b110 )
0,
02
b1001 !
b1001 (
1-
0+
1/
0%
b110 $
b110 '
b110 =
b0 >
#10900000000
12
10
b111 )
1,
b1010 !
b1010 (
0-
1%
b1 >
#11000000000
b1010 !
b1010 (
0-
1+
0%
b111 $
b111 '
b111 =
b0 >
#11100000000
b1011 !
b1011 (
1-
1%
b1 >
#11200000000
05
01
0:
00
06
0"
b0 )
0,
12
07
1;
b1011 !
b1011 (
1-
0+
0/
04
19
0%
b1000 $
b1000 '
b1000 =
b0 >
#11300000000
17
15
11
02
10
b11 )
1,
b1100 !
b1100 (
0-
1%
b1 >
#11400000000
b1100 !
b1100 (
0-
1+
0%
b1001 $
b1001 '
b1001 =
b0 >
#11500000000
b1101 !
b1101 (
1-
1%
b1 >
#11600000000
00
b10 )
0,
02
b1101 !
b1101 (
1-
0+
1/
0%
b1010 $
b1010 '
b1010 =
b0 >
#11700000000
12
10
b11 )
1,
b1110 !
b1110 (
0-
1%
b1 >
#11800000000
b1110 !
b1110 (
0-
1+
0%
b1011 $
b1011 '
b1011 =
b0 >
#11900000000
b1111 !
b1111 (
1-
1%
b1 >
#12000000000
05
0"
01
1;
0:
00
06
b0 )
0,
12
17
b1111 !
b1111 (
1-
0+
0/
14
0%
b1100 $
b1100 '
b1100 =
b0 >
#12100000000
1"
0;
1:
16
07
15
11
02
10
b111 )
1,
b0 !
b0 (
0-
1%
b1 >
#12200000000
b0 !
b0 (
0-
1+
0%
b1101 $
b1101 '
b1101 =
b0 >
#12300000000
b1 !
b1 (
1-
1%
b1 >
#12400000000
00
b110 )
0,
02
b1 !
b1 (
1-
0+
1/
0%
b1110 $
b1110 '
b1110 =
b0 >
#12500000000
12
10
b111 )
1,
b10 !
b10 (
0-
1%
b1 >
#12600000000
b10 !
b10 (
0-
1+
0%
b1111 $
b1111 '
b1111 =
b0 >
#12700000000
b11 !
b11 (
1-
1%
b1 >
#12800000000
0:
06
02
17
0"
00
05
0;
0,
b0 )
01
b100 !
b100 (
0-
0+
0/
04
09
0*
0.
13
0%
b0 $
b0 '
b100 #
b100 &
b100 <
b0 =
b0 >
#12900000000
b101 !
b101 (
1-
1%
b1 >
#13000000000
b101 !
b101 (
1-
1+
0%
b1 $
b1 '
b1 =
b0 >
#13100000000
12
10
b1 )
1,
b110 !
b110 (
0-
1%
b1 >
#13200000000
0;
0:
06
17
05
01
00
12
b0 )
0,
b110 !
b110 (
0-
0+
1/
0%
b10 $
b10 '
b10 =
b0 >
#13300000000
b111 !
b111 (
1-
1%
b1 >
#13400000000
b111 !
b111 (
1-
1+
0%
b11 $
b11 '
b11 =
b0 >
#13500000000
1;
1:
16
07
15
11
02
10
b111 )
1,
b1000 !
b1000 (
0-
1%
b1 >
#13600000000
05
01
00
02
07
b100 )
0,
b1000 !
b1000 (
0-
0+
0/
14
0%
b100 $
b100 '
b100 =
b0 >
#13700000000
b1001 !
b1001 (
1-
1%
b1 >
#13800000000
b1001 !
b1001 (
1-
1+
0%
b101 $
b101 '
b101 =
b0 >
#13900000000
12
10
b101 )
1,
b1010 !
b1010 (
0-
1%
b1 >
#14000000000
07
05
01
00
12
b100 )
0,
b1010 !
b1010 (
0-
0+
1/
0%
b110 $
b110 '
b110 =
b0 >
#14100000000
b1011 !
b1011 (
1-
1%
b1 >
#14200000000
b1011 !
b1011 (
1-
1+
0%
b111 $
b111 '
b111 =
b0 >
#14300000000
17
15
11
02
10
b111 )
1,
b1100 !
b1100 (
0-
1%
b1 >
#14400000000
0:
06
05
01
0"
00
02
17
1;
b0 )
0,
b1100 !
b1100 (
0-
0+
0/
04
19
0%
b1000 $
b1000 '
b1000 =
b0 >
#14500000000
b1101 !
b1101 (
1-
1%
b1 >
#14600000000
b1101 !
b1101 (
1-
1+
0%
b1001 $
b1001 '
b1001 =
b0 >
#14700000000
12
10
b1 )
1,
b1110 !
b1110 (
0-
1%
b1 >
#14800000000
0"
1;
0:
06
17
05
01
00
12
b0 )
0,
b1110 !
b1110 (
0-
0+
1/
0%
b1010 $
b1010 '
b1010 =
b0 >
#14900000000
b1111 !
b1111 (
1-
1%
b1 >
#15000000000
b1111 !
b1111 (
1-
1+
0%
b1011 $
b1011 '
b1011 =
b0 >
#15100000000
1"
0;
1:
16
07
15
11
02
10
b111 )
1,
b0 !
b0 (
0-
1%
b1 >
#15200000000
05
01
00
02
07
b100 )
0,
b0 !
b0 (
0-
0+
0/
14
0%
b1100 $
b1100 '
b1100 =
b0 >
#15300000000
b1 !
b1 (
1-
1%
b1 >
#15400000000
b1 !
b1 (
1-
1+
0%
b1101 $
b1101 '
b1101 =
b0 >
#15500000000
12
10
b101 )
1,
b10 !
b10 (
0-
1%
b1 >
#15600000000
07
05
01
00
12
b100 )
0,
b10 !
b10 (
0-
0+
1/
0%
b1110 $
b1110 '
b1110 =
b0 >
#15700000000
b11 !
b11 (
1-
1%
b1 >
#15800000000
b11 !
b11 (
1-
1+
0%
b1111 $
b1111 '
b1111 =
b0 >
#15900000000
17
15
11
02
10
b111 )
1,
b100 !
b100 (
0-
1%
b1 >
#16000000000
0:
06
05
01
0"
00
02
17
0;
b0 )
0,
b101 !
b101 (
1-
0+
0/
04
09
1*
0%
b0 $
b0 '
b101 #
b101 &
b101 <
b0 =
b0 >
#16100000000
12
10
b1 )
1,
b110 !
b110 (
0-
1%
b1 >
#16200000000
b110 !
b110 (
0-
1+
0%
b1 $
b1 '
b1 =
b0 >
#16300000000
b111 !
b111 (
1-
1%
b1 >
#16400000000
0;
0:
06
17
05
00
01
b0 )
0,
12
b111 !
b111 (
1-
0+
1/
0%
b10 $
b10 '
b10 =
b0 >
#16500000000
1;
1:
16
07
15
11
02
10
b111 )
1,
b1000 !
b1000 (
0-
1%
b1 >
#16600000000
b1000 !
b1000 (
0-
1+
0%
b11 $
b11 '
b11 =
b0 >
#16700000000
b1001 !
b1001 (
1-
1%
b1 >
#16800000000
05
00
01
b100 )
0,
02
07
b1001 !
b1001 (
1-
0+
0/
14
0%
b100 $
b100 '
b100 =
b0 >
#16900000000
12
10
b101 )
1,
b1010 !
b1010 (
0-
1%
b1 >
#17000000000
b1010 !
b1010 (
0-
1+
0%
b101 $
b101 '
b101 =
b0 >
#17100000000
b1011 !
b1011 (
1-
1%
b1 >
#17200000000
07
05
00
01
b100 )
0,
12
b1011 !
b1011 (
1-
0+
1/
0%
b110 $
b110 '
b110 =
b0 >
#17300000000
17
15
11
02
10
b111 )
1,
b1100 !
b1100 (
0-
1%
b1 >
#17400000000
b1100 !
b1100 (
0-
1+
0%
b111 $
b111 '
b111 =
b0 >
#17500000000
b1101 !
b1101 (
1-
1%
b1 >
#17600000000
0:
06
05
00
01
0"
b0 )
0,
02
17
1;
b1101 !
b1101 (
1-
0+
0/
04
19
0%
b1000 $
b1000 '
b1000 =
b0 >
#17700000000
12
10
b1 )
1,
b1110 !
b1110 (
0-
1%
b1 >
#17800000000
b1110 !
b1110 (
0-
1+
0%
b1001 $
b1001 '
b1001 =
b0 >
#17900000000
b1111 !
b1111 (
1-
1%
b1 >
#18000000000
0"
1;
0:
06
17
05
00
01
b0 )
0,
12
b1111 !
b1111 (
1-
0+
1/
0%
b1010 $
b1010 '
b1010 =
b0 >
#18100000000
1"
0;
1:
16
07
15
11
02
10
b111 )
1,
b0 !
b0 (
0-
1%
b1 >
#18200000000
b0 !
b0 (
0-
1+
0%
b1011 $
b1011 '
b1011 =
b0 >
#18300000000
b1 !
b1 (
1-
1%
b1 >
#18400000000
05
00
01
b100 )
0,
02
07
b1 !
b1 (
1-
0+
0/
14
0%
b1100 $
b1100 '
b1100 =
b0 >
#18500000000
12
10
b101 )
1,
b10 !
b10 (
0-
1%
b1 >
#18600000000
b10 !
b10 (
0-
1+
0%
b1101 $
b1101 '
b1101 =
b0 >
#18700000000
b11 !
b11 (
1-
1%
b1 >
#18800000000
07
05
00
01
b100 )
0,
12
b11 !
b11 (
1-
0+
1/
0%
b1110 $
b1110 '
b1110 =
b0 >
#18900000000
17
15
11
02
10
b111 )
1,
b100 !
b100 (
0-
1%
b1 >
#19000000000
b100 !
b100 (
0-
1+
0%
b1111 $
b1111 '
b1111 =
b0 >
#19100000000
b101 !
b101 (
1-
1%
b1 >
#19200000000
0:
06
05
01
12
0"
00
17
0;
b0 )
0,
b110 !
b110 (
0-
0+
0/
04
09
0*
1.
0%
b0 $
b0 '
b110 #
b110 &
b110 <
b0 =
b0 >
#19300000000
b111 !
b111 (
1-
1%
b1 >
#19400000000
b111 !
b111 (
1-
1+
0%
b1 $
b1 '
b1 =
b0 >
#19500000000
1;
1:
16
07
15
11
02
10
b111 )
1,
b1000 !
b1000 (
0-
1%
b1 >
#19600000000
00
02
b110 )
0,
b1000 !
b1000 (
0-
0+
1/
0%
b10 $
b10 '
b10 =
b0 >
#19700000000
b1001 !
b1001 (
1-
1%
b1 >
#19800000000
b1001 !
b1001 (
1-
1+
0%
b11 $
b11 '
b11 =
b0 >
#19900000000
12
10
b111 )
1,
b1010 !
b1010 (
0-
1%
b1 >
#20000000000
05
01
00
12
07
b100 )
0,
b1010 !
b1010 (
0-
0+
0/
14
0%
b100 $
b100 '
b100 =
b0 >
#20100000000
b1011 !
b1011 (
1-
1%
b1 >
#20200000000
b1011 !
b1011 (
1-
1+
0%
b101 $
b101 '
b101 =
b0 >
#20300000000
17
15
11
02
10
b111 )
1,
b1100 !
b1100 (
0-
1%
b1 >
#20400000000
00
02
b110 )
0,
b1100 !
b1100 (
0-
0+
1/
0%
b110 $
b110 '
b110 =
b0 >
#20500000000
b1101 !
b1101 (
1-
1%
b1 >
#20600000000
b1101 !
b1101 (
1-
1+
0%
b111 $
b111 '
b111 =
b0 >
#20700000000
12
10
b111 )
1,
b1110 !
b1110 (
0-
1%
b1 >
#20800000000
0:
06
05
01
0"
00
12
17
1;
b0 )
0,
b1110 !
b1110 (
0-
0+
0/
04
19
0%
b1000 $
b1000 '
b1000 =
b0 >
#20900000000
b1111 !
b1111 (
1-
1%
b1 >
#21000000000
b1111 !
b1111 (
1-
1+
0%
b1001 $
b1001 '
b1001 =
b0 >
#21100000000
1"
0;
1:
16
07
15
11
02
10
b111 )
1,
b0 !
b0 (
0-
1%
b1 >
#21200000000
00
02
b110 )
0,
b0 !
b0 (
0-
0+
1/
0%
b1010 $
b1010 '
b1010 =
b0 >
#21300000000
b1 !
b1 (
1-
1%
b1 >
#21400000000
b1 !
b1 (
1-
1+
0%
b1011 $
b1011 '
b1011 =
b0 >
#21500000000
12
10
b111 )
1,
b10 !
b10 (
0-
1%
b1 >
#21600000000
05
01
00
12
07
b100 )
0,
b10 !
b10 (
0-
0+
0/
14
0%
b1100 $
b1100 '
b1100 =
b0 >
#21700000000
b11 !
b11 (
1-
1%
b1 >
#21800000000
b11 !
b11 (
1-
1+
0%
b1101 $
b1101 '
b1101 =
b0 >
#21900000000
17
15
11
02
10
b111 )
1,
b100 !
b100 (
0-
1%
b1 >
#22000000000
00
02
b110 )
0,
b100 !
b100 (
0-
0+
1/
0%
b1110 $
b1110 '
b1110 =
b0 >
#22100000000
b101 !
b101 (
1-
1%
b1 >
#22200000000
b101 !
b101 (
1-
1+
0%
b1111 $
b1111 '
b1111 =
b0 >
#22300000000
12
10
b111 )
1,
b110 !
b110 (
0-
1%
b1 >
#22400000000
0:
06
05
01
0"
00
12
17
0;
b0 )
0,
b111 !
b111 (
1-
0+
0/
04
09
1*
0%
b0 $
b0 '
b111 #
b111 &
b111 <
b0 =
b0 >
#22500000000
1;
1:
16
07
15
11
02
10
b111 )
1,
b1000 !
b1000 (
0-
1%
b1 >
#22600000000
b1000 !
b1000 (
0-
1+
0%
b1 $
b1 '
b1 =
b0 >
#22700000000
b1001 !
b1001 (
1-
1%
b1 >
#22800000000
00
b110 )
0,
02
b1001 !
b1001 (
1-
0+
1/
0%
b10 $
b10 '
b10 =
b0 >
#22900000000
12
10
b111 )
1,
b1010 !
b1010 (
0-
1%
b1 >
#23000000000
b1010 !
b1010 (
0-
1+
0%
b11 $
b11 '
b11 =
b0 >
#23100000000
b1011 !
b1011 (
1-
1%
b1 >
#23200000000
05
01
00
b100 )
0,
12
07
b1011 !
b1011 (
1-
0+
0/
14
0%
b100 $
b100 '
b100 =
b0 >
#23300000000
17
15
11
02
10
b111 )
1,
b1100 !
b1100 (
0-
1%
b1 >
#23400000000
b1100 !
b1100 (
0-
1+
0%
b101 $
b101 '
b101 =
b0 >
#23500000000
b1101 !
b1101 (
1-
1%
b1 >
#23600000000
00
b110 )
0,
02
b1101 !
b1101 (
1-
0+
1/
0%
b110 $
b110 '
b110 =
b0 >
#23700000000
12
10
b111 )
1,
b1110 !
b1110 (
0-
1%
b1 >
#23800000000
b1110 !
b1110 (
0-
1+
0%
b111 $
b111 '
b111 =
b0 >
#23900000000
b1111 !
b1111 (
1-
1%
b1 >
#24000000000
0:
06
05
01
00
0"
b0 )
0,
12
17
1;
b1111 !
b1111 (
1-
0+
0/
04
19
0%
b1000 $
b1000 '
b1000 =
b0 >
#24100000000
1"
0;
1:
16
07
15
11
02
10
b111 )
1,
b0 !
b0 (
0-
1%
b1 >
#24200000000
b0 !
b0 (
0-
1+
0%
b1001 $
b1001 '
b1001 =
b0 >
#24300000000
b1 !
b1 (
1-
1%
b1 >
#24400000000
00
b110 )
0,
02
b1 !
b1 (
1-
0+
1/
0%
b1010 $
b1010 '
b1010 =
b0 >
#24500000000
12
10
b111 )
1,
b10 !
b10 (
0-
1%
b1 >
#24600000000
b10 !
b10 (
0-
1+
0%
b1011 $
b1011 '
b1011 =
b0 >
#24700000000
b11 !
b11 (
1-
1%
b1 >
#24800000000
05
01
00
b100 )
0,
12
07
b11 !
b11 (
1-
0+
0/
14
0%
b1100 $
b1100 '
b1100 =
b0 >
#24900000000
17
15
11
02
10
b111 )
1,
b100 !
b100 (
0-
1%
b1 >
#25000000000
b100 !
b100 (
0-
1+
0%
b1101 $
b1101 '
b1101 =
b0 >
#25100000000
b101 !
b101 (
1-
1%
b1 >
#25200000000
00
b110 )
0,
02
b101 !
b101 (
1-
0+
1/
0%
b1110 $
b1110 '
b1110 =
b0 >
#25300000000
12
10
b111 )
1,
b110 !
b110 (
0-
1%
b1 >
#25400000000
b110 !
b110 (
0-
1+
0%
b1111 $
b1111 '
b1111 =
b0 >
#25500000000
b111 !
b111 (
1-
1%
b1 >
#25600000000
0"
02
07
1;
00
05
0:
0,
01
b0 )
06
b1000 !
b1000 (
0-
0+
0/
04
09
0*
0.
03
18
0%
b0 $
b0 '
b1000 #
b1000 &
b1000 <
b0 =
b0 >
#25700000000
b1001 !
b1001 (
1-
1%
b1 >
#25800000000
b1001 !
b1001 (
1-
1+
0%
b1 $
b1 '
b1 =
b0 >
#25900000000
12
10
b1 )
1,
b1010 !
b1010 (
0-
1%
b1 >
#26000000000
07
05
01
00
12
b0 )
0,
b1010 !
b1010 (
0-
0+
1/
0%
b10 $
b10 '
b10 =
b0 >
#26100000000
b1011 !
b1011 (
1-
1%
b1 >
#26200000000
b1011 !
b1011 (
1-
1+
0%
b11 $
b11 '
b11 =
b0 >
#26300000000
17
15
11
02
10
b11 )
1,
b1100 !
b1100 (
0-
1%
b1 >
#26400000000
0"
1;
05
0:
01
06
00
02
17
b0 )
0,
b1100 !
b1100 (
0-
0+
0/
14
0%
b100 $
b100 '
b100 =
b0 >
#26500000000
b1101 !
b1101 (
1-
1%
b1 >
#26600000000
b1101 !
b1101 (
1-
1+
0%
b101 $
b101 '
b101 =
b0 >
#26700000000
12
10
b1 )
1,
b1110 !
b1110 (
0-
1%
b1 >
#26800000000
0"
1;
0:
06
17
05
01
00
12
b0 )
0,
b1110 !
b1110 (
0-
0+
1/
0%
b110 $
b110 '
b110 =
b0 >
#26900000000
b1111 !
b1111 (
1-
1%
b1 >
