STARS2025/project5_DrumMachine/source/clkdiv8k.sv
module clkdiv8k (
   input logic clk, rst,
   output logic newclk
);


//reduce reuse recycle


   logic [10:0] count, count_n;
   logic newclk_n;

   always_ff @(posedge clk, posedge rst) begin
      if (rst) begin
           count <= '0;
        //    newclk <= '0;
      end else begin
           count <= count_n;
        //    newclk <= newclk_n;
      end
   end


   always_comb begin
       count_n = count;
       if (count == 11'd1499) begin
           count_n = 0;
           newclk = 1; 
       end else begin
            newclk = 0; 
            count_n = count + 1; 
        //    if (count > 255) begin 
        //     count_n = 'd1; 
        //    end else begin 
        //          count_n = '0;
        //    end 
       end
      
   end


endmodule

STARS2025/project5_DrumMachine/testbench/clkdiv8k_tb.sv
`timescale 1ms/10ns
module clkdiv8k_tb;
    logic clk, rst, en, newclk;
    logic newclk_exp, count_exp;
    clkdiv8k eightk (.clk(clk), .rst(rst), .newclk(newclk)); 

    integer test_case = 0;

    always begin
        #1
        clk = ~clk;
    end

    task reset();
        begin
            rst = 1;
            #8
            rst = 0;
        end
    endtask

    task compare(int expected, int actual);
    begin
        if (expected == actual) begin
            $display("PASSED test case %d", test_case);
        end else begin
            $display("FAILED test case %d\n expected = %d, actual = %d", test_case, expected, actual);
        end
    end
    endtask

    initial begin
        $dumpfile("waves/clkdiv8k.vcd");
        $dumpvars(0, clkdiv8k_tb);

        // Initialize all inputs
        clk = 0;
        en = 1;

        //power on reset
        test_case = 1;
        newclk_exp = 0;
        reset();
        compare(newclk_exp, newclk);
        #8

        //disabled
        test_case = 2;
        en = 0;
        #8
        compare(newclk_exp, newclk);

        //normal operation
        test_case = 3;
        en = 1;
        reset();
        repeat (100) #2;
        newclk_exp = 1;
        compare(newclk_exp, newclk);
        repeat (100) #2;
        newclk_exp = 0;
        compare(newclk_exp, newclk);
        repeat (100) #2;
        newclk_exp = 1;
        compare(newclk_exp, newclk);
        #10

        //mid-operation reset
        test_case = 4;
        #20
        rst = 1;
        #8
        newclk_exp = 0;
        compare(newclk_exp, newclk);
        #5
        $finish;
    end

endmodule

STARS2025/project5/waves/clkdiv8k.vcd
$date
	Thu Jun 26 16:26:40 2025
$end
$version
	Icarus Verilog
$end
$timescale
	10ns
$end
$scope module clkdiv8k_tb $end
$var wire 1 ! newclk $end
$var reg 1 " clk $end
$var reg 1 # en $end
$var reg 1 $ newclk_exp $end
$var reg 1 % rst $end
$var integer 32 & test_case [31:0] $end
$scope module eightk $end
$var wire 1 " clk $end
$var wire 1 % rst $end
$var reg 11 ' count [10:0] $end
$var reg 11 ( count_n [10:0] $end
$var reg 1 ! newclk $end
$upscope $end
$scope task compare $end
$var integer 32 ) actual [31:0] $end
$var integer 32 * expected [31:0] $end
$upscope $end
$scope task reset $end
$upscope $end
$upscope $end
$enddefinitions $end
$comment Show the parameter values. $end
$dumpall
$end
#0
$dumpvars
b0 *
b0 )
b1 (
b0 '
b1 &
1%
0$
1#
0"
0!
$end
#100000
1"
#200000
0"
#300000
1"
#400000
0"
#500000
1"
#600000
0"
#700000
1"
#800000
0"
0%
#900000
b10 (
b1 '
1"
#1000000
0"
#1100000
b11 (
b10 '
1"
#1200000
0"
#1300000
b100 (
b11 '
1"
#1400000
0"
#1500000
b101 (
b100 '
1"
#1600000
0"
0#
b10 &
#1700000
b110 (
b101 '
1"
#1800000
0"
#1900000
b111 (
b110 '
1"
#2000000
0"
#2100000
b1000 (
b111 '
1"
#2200000
0"
#2300000
b1001 (
b1000 '
1"
#2400000
b1 (
b0 '
0"
1%
1#
b11 &
#2500000
1"
#2600000
0"
#2700000
1"
#2800000
0"
#2900000
1"
#3000000
0"
#3100000
1"
#3200000
0"
0%
#3300000
b10 (
b1 '
1"
#3400000
0"
#3500000
b11 (
b10 '
1"
#3600000
0"
#3700000
b100 (
b11 '
1"
#3800000
0"
#3900000
b101 (
b100 '
1"
#4000000
0"
#4100000
b110 (
b101 '
1"
#4200000
0"
#4300000
b111 (
b110 '
1"
#4400000
0"
#4500000
b1000 (
b111 '
1"
#4600000
0"
#4700000
b1001 (
b1000 '
1"
#4800000
0"
#4900000
b1010 (
b1001 '
1"
#5000000
0"
#5100000
b1011 (
b1010 '
1"
#5200000
0"
#5300000
b1100 (
b1011 '
1"
#5400000
0"
#5500000
b1101 (
b1100 '
1"
#5600000
0"
#5700000
b1110 (
b1101 '
1"
#5800000
0"
#5900000
b1111 (
b1110 '
1"
#6000000
0"
#6100000
b10000 (
b1111 '
1"
#6200000
0"
#6300000
b10001 (
b10000 '
1"
#6400000
0"
#6500000
b10010 (
b10001 '
1"
#6600000
0"
#6700000
b10011 (
b10010 '
1"
#6800000
0"
#6900000
b10100 (
b10011 '
1"
#7000000
0"
#7100000
b10101 (
b10100 '
1"
#7200000
0"
#7300000
b10110 (
b10101 '
1"
#7400000
0"
#7500000
b10111 (
b10110 '
1"
#7600000
0"
#7700000
b11000 (
b10111 '
1"
#7800000
0"
#7900000
b11001 (
b11000 '
1"
#8000000
0"
#8100000
b11010 (
b11001 '
1"
#8200000
0"
#8300000
b11011 (
b11010 '
1"
#8400000
0"
#8500000
b11100 (
b11011 '
1"
#8600000
0"
#8700000
b11101 (
b11100 '
1"
#8800000
0"
#8900000
b11110 (
b11101 '
1"
#9000000
0"
#9100000
b11111 (
b11110 '
1"
#9200000
0"
#9300000
b100000 (
b11111 '
1"
#9400000
0"
#9500000
b100001 (
b100000 '
1"
#9600000
0"
#9700000
b100010 (
b100001 '
1"
#9800000
0"
#9900000
b100011 (
b100010 '
1"
#10000000
0"
#10100000
b100100 (
b100011 '
1"
#10200000
0"
#10300000
b100101 (
b100100 '
1"
#10400000
0"
#10500000
b100110 (
b100101 '
1"
#10600000
0"
#10700000
b100111 (
b100110 '
1"
#10800000
0"
#10900000
b101000 (
b100111 '
1"
#11000000
0"
#11100000
b101001 (
b101000 '
1"
#11200000
0"
#11300000
b101010 (
b101001 '
1"
#11400000
0"
#11500000
b101011 (
b101010 '
1"
#11600000
0"
#11700000
b101100 (
b101011 '
1"
#11800000
0"
#11900000
b101101 (
b101100 '
1"
#12000000
0"
#12100000
b101110 (
b101101 '
1"
#12200000
0"
#12300000
b101111 (
b101110 '
1"
#12400000
0"
#12500000
b110000 (
b101111 '
1"
#12600000
0"
#12700000
b110001 (
b110000 '
1"
#12800000
0"
#12900000
b110010 (
b110001 '
1"
#13000000
0"
#13100000
b110011 (
b110010 '
1"
#13200000
0"
#13300000
b110100 (
b110011 '
1"
#13400000
0"
#13500000
b110101 (
b110100 '
1"
#13600000
0"
#13700000
b110110 (
b110101 '
1"
#13800000
0"
#13900000
b110111 (
b110110 '
1"
#14000000
0"
#14100000
b111000 (
b110111 '
1"
#14200000
0"
#14300000
b111001 (
b111000 '
1"
#14400000
0"
#14500000
b111010 (
b111001 '
1"
#14600000
0"
#14700000
b111011 (
b111010 '
1"
#14800000
0"
#14900000
b111100 (
b111011 '
1"
#15000000
0"
#15100000
b111101 (
b111100 '
1"
#15200000
0"
#15300000
b111110 (
b111101 '
1"
#15400000
0"
#15500000
b111111 (
b111110 '
1"
#15600000
0"
#15700000
b1000000 (
b111111 '
1"
#15800000
0"
#15900000
b1000001 (
b1000000 '
1"
#16000000
0"
#16100000
b1000010 (
b1000001 '
1"
#16200000
0"
#16300000
b1000011 (
b1000010 '
1"
#16400000
0"
#16500000
b1000100 (
b1000011 '
1"
#16600000
0"
#16700000
b1000101 (
b1000100 '
1"
#16800000
0"
#16900000
b1000110 (
b1000101 '
1"
#17000000
0"
#17100000
b1000111 (
b1000110 '
1"
#17200000
0"
#17300000
b1001000 (
b1000111 '
1"
#17400000
0"
#17500000
b1001001 (
b1001000 '
1"
#17600000
0"
#17700000
b1001010 (
b1001001 '
1"
#17800000
0"
#17900000
b1001011 (
b1001010 '
1"
#18000000
0"
#18100000
b1001100 (
b1001011 '
1"
#18200000
0"
#18300000
b1001101 (
b1001100 '
1"
#18400000
0"
#18500000
b1001110 (
b1001101 '
1"
#18600000
0"
#18700000
b1001111 (
b1001110 '
1"
#18800000
0"
#18900000
b1010000 (
b1001111 '
1"
#19000000
0"
#19100000
b1010001 (
b1010000 '
1"
#19200000
0"
#19300000
b1010010 (
b1010001 '
1"
#19400000
0"
#19500000
b1010011 (
b1010010 '
1"
#19600000
0"
#19700000
b1010100 (
b1010011 '
1"
#19800000
0"
#19900000
b1010101 (
b1010100 '
1"
#20000000
0"
#20100000
b1010110 (
b1010101 '
1"
#20200000
0"
#20300000
b1010111 (
b1010110 '
1"
#20400000
0"
#20500000
b1011000 (
b1010111 '
1"
#20600000
0"
#20700000
b1011001 (
b1011000 '
1"
#20800000
0"
#20900000
b1011010 (
b1011001 '
1"
#21000000
0"
#21100000
b1011011 (
b1011010 '
1"
#21200000
0"
#21300000
b1011100 (
b1011011 '
1"
#21400000
0"
#21500000
b1011101 (
b1011100 '
1"
#21600000
0"
#21700000
b1011110 (
b1011101 '
1"
#21800000
0"
#21900000
b1011111 (
b1011110 '
1"
#22000000
0"
#22100000
b1100000 (
b1011111 '
1"
#22200000
0"
#22300000
b1100001 (
b1100000 '
1"
#22400000
0"
#22500000
b1100010 (
b1100001 '
1"
#22600000
0"
#22700000
b1100011 (
b1100010 '
1"
#22800000
0"
#22900000
b1100100 (
b1100011 '
1"
#23000000
0"
#23100000
b1100101 (
b1100100 '
1"
#23200000
0"
b1 *
1$
#23300000
b1100110 (
b1100101 '
1"
#23400000
0"
#23500000
b1100111 (
b1100110 '
1"
#23600000
0"
#23700000
b1101000 (
b1100111 '
1"
#23800000
0"
#23900000
b1101001 (
b1101000 '
1"
#24000000
0"
#24100000
b1101010 (
b1101001 '
1"
#24200000
0"
#24300000
b1101011 (
b1101010 '
1"
#24400000
0"
#24500000
b1101100 (
b1101011 '
1"
#24600000
0"
#24700000
b1101101 (
b1101100 '
1"
#24800000
0"
#24900000
b1101110 (
b1101101 '
1"
#25000000
0"
#25100000
b1101111 (
b1101110 '
1"
#25200000
0"
#25300000
b1110000 (
b1101111 '
1"
#25400000
0"
#25500000
b1110001 (
b1110000 '
1"
#25600000
0"
#25700000
b1110010 (
b1110001 '
1"
#25800000
0"
#25900000
b1110011 (
b1110010 '
1"
#26000000
0"
#26100000
b1110100 (
b1110011 '
1"
#26200000
0"
#26300000
b1110101 (
b1110100 '
1"
#26400000
0"
#26500000
b1110110 (
b1110101 '
1"
#26600000
0"
#26700000
b1110111 (
b1110110 '
1"
#26800000
0"
#26900000
b1111000 (
b1110111 '
1"
#27000000
0"
#27100000
b1111001 (
b1111000 '
1"
#27200000
0"
#27300000
b1111010 (
b1111001 '
1"
#27400000
0"
#27500000
b1111011 (
b1111010 '
1"
#27600000
0"
#27700000
b1111100 (
b1111011 '
1"
#27800000
0"
#27900000
b1111101 (
b1111100 '
1"
#28000000
0"
#28100000
b1111110 (
b1111101 '
1"
#28200000
0"
#28300000
b1111111 (
b1111110 '
1"
#28400000
0"
#28500000
b10000000 (
b1111111 '
1"
#28600000
0"
#28700000
b10000001 (
b10000000 '
1"
#28800000
0"
#28900000
b10000010 (
b10000001 '
1"
#29000000
0"
#29100000
b10000011 (
b10000010 '
1"
#29200000
0"
#29300000
b10000100 (
b10000011 '
1"
#29400000
0"
#29500000
b10000101 (
b10000100 '
1"
#29600000
0"
#29700000
b10000110 (
b10000101 '
1"
#29800000
0"
#29900000
b10000111 (
b10000110 '
1"
#30000000
0"
#30100000
b10001000 (
b10000111 '
1"
#30200000
0"
#30300000
b10001001 (
b10001000 '
1"
#30400000
0"
#30500000
b10001010 (
b10001001 '
1"
#30600000
0"
#30700000
b10001011 (
b10001010 '
1"
#30800000
0"
#30900000
b10001100 (
b10001011 '
1"
#31000000
0"
#31100000
b10001101 (
b10001100 '
1"
#31200000
0"
#31300000
b10001110 (
b10001101 '
1"
#31400000
0"
#31500000
b10001111 (
b10001110 '
1"
#31600000
0"
#31700000
b10010000 (
b10001111 '
1"
#31800000
0"
#31900000
b10010001 (
b10010000 '
1"
#32000000
0"
#32100000
b10010010 (
b10010001 '
1"
#32200000
0"
#32300000
b10010011 (
b10010010 '
1"
#32400000
0"
#32500000
b10010100 (
b10010011 '
1"
#32600000
0"
#32700000
b10010101 (
b10010100 '
1"
#32800000
0"
#32900000
b10010110 (
b10010101 '
1"
#33000000
0"
#33100000
b10010111 (
b10010110 '
1"
#33200000
0"
#33300000
b10011000 (
b10010111 '
1"
#33400000
0"
#33500000
b10011001 (
b10011000 '
1"
#33600000
0"
#33700000
b10011010 (
b10011001 '
1"
#33800000
0"
#33900000
b10011011 (
b10011010 '
1"
#34000000
0"
#34100000
b10011100 (
b10011011 '
1"
#34200000
0"
#34300000
b10011101 (
b10011100 '
1"
#34400000
0"
#34500000
b10011110 (
b10011101 '
1"
#34600000
0"
#34700000
b10011111 (
b10011110 '
1"
#34800000
0"
#34900000
b10100000 (
b10011111 '
1"
#35000000
0"
#35100000
b10100001 (
b10100000 '
1"
#35200000
0"
#35300000
b10100010 (
b10100001 '
1"
#35400000
0"
#35500000
b10100011 (
b10100010 '
1"
#35600000
0"
#35700000
b10100100 (
b10100011 '
1"
#35800000
0"
#35900000
b10100101 (
b10100100 '
1"
#36000000
0"
#36100000
b10100110 (
b10100101 '
1"
#36200000
0"
#36300000
b10100111 (
b10100110 '
1"
#36400000
0"
#36500000
b10101000 (
b10100111 '
1"
#36600000
0"
#36700000
b10101001 (
b10101000 '
1"
#36800000
0"
#36900000
b10101010 (
b10101001 '
1"
#37000000
0"
#37100000
b10101011 (
b10101010 '
1"
#37200000
0"
#37300000
b10101100 (
b10101011 '
1"
#37400000
0"
#37500000
b10101101 (
b10101100 '
1"
#37600000
0"
#37700000
b10101110 (
b10101101 '
1"
#37800000
0"
#37900000
b10101111 (
b10101110 '
1"
#38000000
0"
#38100000
b10110000 (
b10101111 '
1"
#38200000
0"
#38300000
b10110001 (
b10110000 '
1"
#38400000
0"
#38500000
b10110010 (
b10110001 '
1"
#38600000
0"
#38700000
b10110011 (
b10110010 '
1"
#38800000
0"
#38900000
b10110100 (
b10110011 '
1"
#39000000
0"
#39100000
b10110101 (
b10110100 '
1"
#39200000
0"
#39300000
b10110110 (
b10110101 '
1"
#39400000
0"
#39500000
b10110111 (
b10110110 '
1"
#39600000
0"
#39700000
b10111000 (
b10110111 '
1"
#39800000
0"
#39900000
b10111001 (
b10111000 '
1"
#40000000
0"
#40100000
b10111010 (
b10111001 '
1"
#40200000
0"
#40300000
b10111011 (
b10111010 '
1"
#40400000
0"
#40500000
b10111100 (
b10111011 '
1"
#40600000
0"
#40700000
b10111101 (
b10111100 '
1"
#40800000
0"
#40900000
b10111110 (
b10111101 '
1"
#41000000
0"
#41100000
b10111111 (
b10111110 '
1"
#41200000
0"
#41300000
b11000000 (
b10111111 '
1"
#41400000
0"
#41500000
b11000001 (
b11000000 '
1"
#41600000
0"
#41700000
b11000010 (
b11000001 '
1"
#41800000
0"
#41900000
b11000011 (
b11000010 '
1"
#42000000
0"
#42100000
b11000100 (
b11000011 '
1"
#42200000
0"
#42300000
b11000101 (
b11000100 '
1"
#42400000
0"
#42500000
b11000110 (
b11000101 '
1"
#42600000
0"
#42700000
b11000111 (
b11000110 '
1"
#42800000
0"
#42900000
b11001000 (
b11000111 '
1"
#43000000
0"
#43100000
b11001001 (
b11001000 '
1"
#43200000
0"
b0 *
0$
#43300000
b11001010 (
b11001001 '
1"
#43400000
0"
#43500000
b11001011 (
b11001010 '
1"
#43600000
0"
#43700000
b11001100 (
b11001011 '
1"
#43800000
0"
#43900000
b11001101 (
b11001100 '
1"
#44000000
0"
#44100000
b11001110 (
b11001101 '
1"
#44200000
0"
#44300000
b11001111 (
b11001110 '
1"
#44400000
0"
#44500000
b11010000 (
b11001111 '
1"
#44600000
0"
#44700000
b11010001 (
b11010000 '
1"
#44800000
0"
#44900000
b11010010 (
b11010001 '
1"
#45000000
0"
#45100000
b11010011 (
b11010010 '
1"
#45200000
0"
#45300000
b11010100 (
b11010011 '
1"
#45400000
0"
#45500000
b11010101 (
b11010100 '
1"
#45600000
0"
#45700000
b11010110 (
b11010101 '
1"
#45800000
0"
#45900000
b11010111 (
b11010110 '
1"
#46000000
0"
#46100000
b11011000 (
b11010111 '
1"
#46200000
0"
#46300000
b11011001 (
b11011000 '
1"
#46400000
0"
#46500000
b11011010 (
b11011001 '
1"
#46600000
0"
#46700000
b11011011 (
b11011010 '
1"
#46800000
0"
#46900000
b11011100 (
b11011011 '
1"
#47000000
0"
#47100000
b11011101 (
b11011100 '
1"
#47200000
0"
#47300000
b11011110 (
b11011101 '
1"
#47400000
0"
#47500000
b11011111 (
b11011110 '
1"
#47600000
0"
#47700000
b11100000 (
b11011111 '
1"
#47800000
0"
#47900000
b11100001 (
b11100000 '
1"
#48000000
0"
#48100000
b11100010 (
b11100001 '
1"
#48200000
0"
#48300000
b11100011 (
b11100010 '
1"
#48400000
0"
#48500000
b11100100 (
b11100011 '
1"
#48600000
0"
#48700000
b11100101 (
b11100100 '
1"
#48800000
0"
#48900000
b11100110 (
b11100101 '
1"
#49000000
0"
#49100000
b11100111 (
b11100110 '
1"
#49200000
0"
#49300000
b11101000 (
b11100111 '
1"
#49400000
0"
#49500000
b11101001 (
b11101000 '
1"
#49600000
0"
#49700000
b11101010 (
b11101001 '
1"
#49800000
0"
#49900000
b11101011 (
b11101010 '
1"
#50000000
0"
#50100000
b11101100 (
b11101011 '
1"
#50200000
0"
#50300000
b11101101 (
b11101100 '
1"
#50400000
0"
#50500000
b11101110 (
b11101101 '
1"
#50600000
0"
#50700000
b11101111 (
b11101110 '
1"
#50800000
0"
#50900000
b11110000 (
b11101111 '
1"
#51000000
0"
#51100000
b11110001 (
b11110000 '
1"
#51200000
0"
#51300000
b11110010 (
b11110001 '
1"
#51400000
0"
#51500000
b11110011 (
b11110010 '
1"
#51600000
0"
#51700000
b11110100 (
b11110011 '
1"
#51800000
0"
#51900000
b11110101 (
b11110100 '
1"
#52000000
0"
#52100000
b11110110 (
b11110101 '
1"
#52200000
0"
#52300000
b11110111 (
b11110110 '
1"
#52400000
0"
#52500000
b11111000 (
b11110111 '
1"
#52600000
0"
#52700000
b11111001 (
b11111000 '
1"
#52800000
0"
#52900000
b11111010 (
b11111001 '
1"
#53000000
0"
#53100000
b11111011 (
b11111010 '
1"
#53200000
0"
#53300000
b11111100 (
b11111011 '
1"
#53400000
0"
#53500000
b11111101 (
b11111100 '
1"
#53600000
0"
#53700000
b11111110 (
b11111101 '
1"
#53800000
0"
#53900000
b11111111 (
b11111110 '
1"
#54000000
0"
#54100000
b100000000 (
b11111111 '
1"
#54200000
0"
#54300000
b100000001 (
b100000000 '
1"
#54400000
0"
#54500000
b100000010 (
b100000001 '
1"
#54600000
0"
#54700000
b100000011 (
b100000010 '
1"
#54800000
0"
#54900000
b100000100 (
b100000011 '
1"
#55000000
0"
#55100000
b100000101 (
b100000100 '
1"
#55200000
0"
#55300000
b100000110 (
b100000101 '
1"
#55400000
0"
#55500000
b100000111 (
b100000110 '
1"
#55600000
0"
#55700000
b100001000 (
b100000111 '
1"
#55800000
0"
#55900000
b100001001 (
b100001000 '
1"
#56000000
0"
#56100000
b100001010 (
b100001001 '
1"
#56200000
0"
#56300000
b100001011 (
b100001010 '
1"
#56400000
0"
#56500000
b100001100 (
b100001011 '
1"
#56600000
0"
#56700000
b100001101 (
b100001100 '
1"
#56800000
0"
#56900000
b100001110 (
b100001101 '
1"
#57000000
0"
#57100000
b100001111 (
b100001110 '
1"
#57200000
0"
#57300000
b100010000 (
b100001111 '
1"
#57400000
0"
#57500000
b100010001 (
b100010000 '
1"
#57600000
0"
#57700000
b100010010 (
b100010001 '
1"
#57800000
0"
#57900000
b100010011 (
b100010010 '
1"
#58000000
0"
#58100000
b100010100 (
b100010011 '
1"
#58200000
0"
#58300000
b100010101 (
b100010100 '
1"
#58400000
0"
#58500000
b100010110 (
b100010101 '
1"
#58600000
0"
#58700000
b100010111 (
b100010110 '
1"
#58800000
0"
#58900000
b100011000 (
b100010111 '
1"
#59000000
0"
#59100000
b100011001 (
b100011000 '
1"
#59200000
0"
#59300000
b100011010 (
b100011001 '
1"
#59400000
0"
#59500000
b100011011 (
b100011010 '
1"
#59600000
0"
#59700000
b100011100 (
b100011011 '
1"
#59800000
0"
#59900000
b100011101 (
b100011100 '
1"
#60000000
0"
#60100000
b100011110 (
b100011101 '
1"
#60200000
0"
#60300000
b100011111 (
b100011110 '
1"
#60400000
0"
#60500000
b100100000 (
b100011111 '
1"
#60600000
0"
#60700000
b100100001 (
b100100000 '
1"
#60800000
0"
#60900000
b100100010 (
b100100001 '
1"
#61000000
0"
#61100000
b100100011 (
b100100010 '
1"
#61200000
0"
#61300000
b100100100 (
b100100011 '
1"
#61400000
0"
#61500000
b100100101 (
b100100100 '
1"
#61600000
0"
#61700000
b100100110 (
b100100101 '
1"
#61800000
0"
#61900000
b100100111 (
b100100110 '
1"
#62000000
0"
#62100000
b100101000 (
b100100111 '
1"
#62200000
0"
#62300000
b100101001 (
b100101000 '
1"
#62400000
0"
#62500000
b100101010 (
b100101001 '
1"
#62600000
0"
#62700000
b100101011 (
b100101010 '
1"
#62800000
0"
#62900000
b100101100 (
b100101011 '
1"
#63000000
0"
#63100000
b100101101 (
b100101100 '
1"
#63200000
0"
b1 *
1$
#63300000
b100101110 (
b100101101 '
1"
#63400000
0"
#63500000
b100101111 (
b100101110 '
1"
#63600000
0"
#63700000
b100110000 (
b100101111 '
1"
#63800000
0"
#63900000
b100110001 (
b100110000 '
1"
#64000000
0"
#64100000
b100110010 (
b100110001 '
1"
#64200000
0"
b100 &
#64300000
b100110011 (
b100110010 '
1"
#64400000
0"
#64500000
b100110100 (
b100110011 '
1"
#64600000
0"
#64700000
b100110101 (
b100110100 '
1"
#64800000
0"
#64900000
b100110110 (
b100110101 '
1"
#65000000
0"
#65100000
b100110111 (
b100110110 '
1"
#65200000
0"
#65300000
b100111000 (
b100110111 '
1"
#65400000
0"
#65500000
b100111001 (
b100111000 '
1"
#65600000
0"
#65700000
b100111010 (
b100111001 '
1"
#65800000
0"
#65900000
b100111011 (
b100111010 '
1"
#66000000
0"
#66100000
b100111100 (
b100111011 '
1"
#66200000
b1 (
b0 '
0"
1%
#66300000
1"
#66400000
0"
#66500000
1"
#66600000
0"
#66700000
1"
#66800000
0"
#66900000
1"
#67000000
0"
b0 *
0$
